otter/__init__.py
otter/__main__.py
otter/api.py
otter/config.py
otter/const.py
otter/errors.py
otter/funcs.py
otter/model.py
otter/otter.py
otter/database/__init__.py
otter/database/model.py
otter/database/query.py
otter/odoo/__init__.py
otter/odoo/rest.py
otter/util/__init__.py
otter/util/cli.py
otter/util/date.py
otter/util/math.py
otter/util/serialize.py
odoo_otter-0.1.0.dist-info/LICENSE
odoo_otter-0.1.0.dist-info/METADATA
odoo_otter-0.1.0.dist-info/WHEEL
odoo_otter-0.1.0.dist-info/entry_points.txt
odoo_otter-0.1.0.dist-info/top_level.txt
odoo_otter-0.1.0.dist-info/RECORD
