Metadata-Version: 2.1
Name: odoo-otter
Version: 0.1.0
Summary: Otter - The Odoo time tracker
Home-page: https://github.com/pathob/odoo-otter
Author: Patrick Hobusch
Author-email: pathob@users.noreply.github.com
License: Apache 2.0
Platform: UNKNOWN
Requires-Dist: requests (~=2.28)
Requires-Dist: SQLAlchemy (~=1.4)
Requires-Dist: colorama (~=0.4)
Requires-Dist: setuptools (~=67.5)
